yr_meteogram_util/__init__.py
yr_meteogram_util/extract_info.py
yr_meteogram_util/fetch.py
yr_meteogram_util-0.2.6.dist-info/METADATA
yr_meteogram_util-0.2.6.dist-info/WHEEL
yr_meteogram_util-0.2.6.dist-info/licenses/LICENSE.txt
yr_meteogram_util-0.2.6.dist-info/RECORD
