Metadata-Version: 2.4
Name: yr_meteogram_util
Version: 0.2.6
Summary: A package for downloading and maniuplating meteograms from YR
Project-URL: Homepage, https://github.com/d95andek/yr_meteogram_util
Project-URL: Issues, https://github.com/d95andek/yr_meteogram_util/issues
Author-email: Andreas Gunnerås <andreas@gunneras.se>
License-Expression: MIT
License-File: LICENSE.txt
Classifier: Operating System :: OS Independent
Classifier: Programming Language :: Python :: 3
Requires-Python: >=3.10
Requires-Dist: aiohttp>=3.10
